{
  "version": "7",
  "dialect": "postgresql",
  "entries": [
    {
      "idx": 0,
      "version": "7",
      "when": 1755672111623,
      "tag": "0000_nosy_redwing",
      "breakpoints": true
    },
    {
      "idx": 1,
      "version": "7",
      "when": 1758003214035,
      "tag": "0001_chief_giant_man",
      "breakpoints": true
    },
    {
      "idx": 2,
      "version": "7",
      "when": 1758033550681,
      "tag": "0002_cute_thor",
      "breakpoints": true
    },
    {
      "idx": 3,
      "version": "7",
      "when": 1758102185578,
      "tag": "0003_chunky_wolfpack",
      "breakpoints": true
    },
    {
      "idx": 4,
      "version": "7",
      "when": 1758179440357,
      "tag": "0004_nebulous_mister_sinister",
      "breakpoints": true
    },
    {
      "idx": 5,
      "version": "7",
      "when": 1758272487766,
      "tag": "0005_black_sunfire",
      "breakpoints": true
    },
    {
      "idx": 6,
      "version": "7",
      "when": 1758276529071,
      "tag": "0006_cultured_spiral",
      "breakpoints": true
    },
    {
      "idx": 7,
      "version": "7",
      "when": 1758296159888,
      "tag": "0007_bored_hedge_knight",
      "breakpoints": true
    },
    {
      "idx": 8,
      "version": "7",
      "when": 1758296295675,
      "tag": "0008_ambitious_microbe",
      "breakpoints": true
    },
    {
      "idx": 9,
      "version": "7",
      "when": 1758316187394,
      "tag": "0009_lying_aaron_stack",
      "breakpoints": true
    },
    {
      "idx": 10,
      "version": "7",
      "when": 1758359347419,
      "tag": "0010_uneven_lilandra",
      "breakpoints": true
    }
  ]
}